{"video_scanline_phase_shift_offset":0,"filter_type":1,"head_switching_mid_line_jitter":0.029999999329447746,"tracking_noise_snow_intensity":0.02500000037252903,"chroma_lowpass_out":2,"tracking_noise_wave_intensity":15,"ringing_frequency":0.44999998807907104,"chroma_phase_noise_intensity":0.0010000000474974513,"vhs_sharpen":0.25,"vhs_tape_speed":2,"vhs_edge_wave_frequency":0.20999999344348907,"tracking_noise":true,"composite_noise_frequency":0,"chroma_phase_error":0,"head_switching_mid_line_position":1,"chroma_noise_frequency":0.05000000074505806,"ringing_power":4,"vhs_sharpen_enabled":true,"video_scanline_phase_shift":2,"vhs_sharpen_frequency":1,"vhs_settings":true,"luma_noise":true,"bandwidth_scale":0.125,"vhs_chroma_loss":0.0002500000118743628,"chroma_noise_detail":2,"head_switching_start_mid_line":true,"vhs_edge_wave_enabled":true,"input_luma_filter":2,"chroma_lowpass_in":2,"composite_noise":true,"tracking_noise_noise_intensity":0.25,"ringing_scale":4,"snow_anisotropy":0,"luma_smear":0.5,"head_switching_height":5,"chroma_noise_intensity":0.10000000149011612,"vhs_chroma_vert_blend":true,"vhs_edge_wave_speed":10,"chroma_delay_horizontal":0,"composite_preemphasis":0.15000000596046448,"tracking_noise_height":0,"vhs_edge_wave":4.199999809265137,"version":1,"head_switching_horizontal_shift":33,"head_switching_offset":3,"luma_noise_frequency":0.5,"random_seed":0,"luma_noise_intensity":0.009999999776482582,"head_switching":true,"chroma_noise":true,"snow_intensity":0,"tracking_noise_snow_anisotropy":0.25,"vhs_edge_wave_detail":2,"chroma_delay_vertical":0,"composite_noise_detail":1,"chroma_demodulation":1,"luma_noise_detail":1,"use_field":0,"composite_noise_intensity":0,"ringing":true}